yenpoint_1satordinals/__init__.py
yenpoint_1satordinals/core.py
yenpoint_1satordinals-0.1.1.dist-info/LICENSE.md
yenpoint_1satordinals-0.1.1.dist-info/METADATA
yenpoint_1satordinals-0.1.1.dist-info/WHEEL
yenpoint_1satordinals-0.1.1.dist-info/top_level.txt
yenpoint_1satordinals-0.1.1.dist-info/RECORD
