Metadata-Version: 2.1
Name: yenpoint_1satordinals
Version: 0.1.1
Summary: A library for creating 1Sat Ordinals NFTs on BSV blockchain
Author-email: Ken Sato <info@yenpoint.jp>
Project-URL: website, https://yenpoint.com
Project-URL: Repository, https://github.com/Yenpoint/yenpoint_1satordinals
Keywords: blockchain,BSV,NFT,ordinals
Requires-Python: >=3.7
License-File: LICENSE.md
Requires-Dist: bsv-sdk>=0.5.2
Provides-Extra: dev
Requires-Dist: pytest>=6.0; extra == "dev"
Requires-Dist: pytest-cov; extra == "dev"
